cdt_queue2/__init__.py
cdt_queue2/ipc_messages.py
cdt_queue2/queue_application.py
cdt_queue2/queue_base.py
cdt_queue2/queue_client.py
cdt_queue2/queue_connection_prcs.py
cdt_queue2/queue_handler.py
cdt_queue2/queue_rpc.py
cdt_queue2/queue_server.py
cdt_queue2/test/__init__.py
cdt_queue2/test/test_app.py
cdt_queue2/test/test_base.py
cdt_queue2/test/test_client.py
cdt_queue2/test/test_connection_prcs.py
cdt_queue2/test/test_handler.py
cdt_queue2/test/test_qrpc.py
cdt_queue2/test/test_server.py
cdt_queue2/test/mocks/__init__.py
cdt_queue2/test/mocks/queue_t.py
cdt_queue2/test/synchron/__init__.py
cdt_queue2/test/synchron/test_app.py
cdt_queue2/test/synchron/test_base.py
cdt_queue2/test/synchron/test_handler.py
cdt_queue2/test/synchron/test_recv.py
cdt_queue2/test/synchron/test_rpc.py
cdt_queue2/test/synchron/test_send.py
cdt_queue2/test/synchron/mocks/__init__.py
cdt_queue2/test/synchron/mocks/queue_application.py
cdt_queue2/test/synchron/mocks/queue_base.py
cdt_queue2/test/synchron/mocks/queue_client.py
cdt_queue2/test/synchron/mocks/queue_handler.py
cdt_queue2/test/synchron/mocks/queue_loopback.py
cdt_queue2/test/synchron/mocks/queue_rpc.py
cdt_queue2/test/synchron/mocks/queue_server.py
cdt_queue2-4.0.1.20230331125100.dist-info/LICENSE
cdt_queue2-4.0.1.20230331125100.dist-info/METADATA
cdt_queue2-4.0.1.20230331125100.dist-info/WHEEL
cdt_queue2-4.0.1.20230331125100.dist-info/top_level.txt
cdt_queue2-4.0.1.20230331125100.dist-info/RECORD
