Metadata-Version: 2.1
Name: cdt-queue2
Version: 4.0.1.20230331125100
Summary: Code for CDT message queue management
Home-page: UNKNOWN
Author: UNKNOWN
Author-email: UNKNOWN
License: Apache2.0
Platform: UNKNOWN
Requires-Dist: pika (==1.1.0)
